{
    "@module": "dpdata.system",
    "@class": "LabeledSystem",
    "data": {
        "atom_numbs": [
            6,
            9
        ],
        "atom_names": [
            "Bi",
            "Te"
        ],
        "atom_types": {
            "@module": "numpy",
            "@class": "array",
            "dtype": "int64",
            "data": [
                0,
                1,
                1,
                0,
                1,
                1,
                0,
                1,
                0,
                1,
                0,
                1,
                1,
                0,
                1
            ]
        },
        "orig": {
            "@module": "numpy",
            "@class": "array",
            "dtype": "int64",
            "data": [
                0,
                0,
                0
            ]
        },
        "cells": {
            "@module": "numpy",
            "@class": "array",
            "dtype": "float64",
            "data": [
                [
                    [
                        4.4022152997,
                        0.0,
                        0.0
                    ],
                    [
                        -2.20110823,
                        3.812430282,
                        0.0
                    ],
                    [
                        -1e-10,
                        -1e-10,
                        30.400223137
                    ]
                ],
                [
                    [
                        4.4022152997,
                        0.0,
                        0.0
                    ],
                    [
                        -2.20110823,
                        3.812430282,
                        0.0
                    ],
                    [
                        -1e-10,
                        -1e-10,
                        30.400223137
                    ]
                ]
            ]
        },
        "coords": {
            "@module": "numpy",
            "@class": "array",
            "dtype": "float64",
            "data": [
                [
                    [
                        -2.5878812174682955e-06,
                        2.5416214588033865,
                        2.0390797668027063
                    ],
                    [
                        2.2011096575620375,
                        1.2708088231774333,
                        3.791759031431736
                    ],
                    [
                        2.480009347273485e-08,
                        4.2900134233625216e-08,
                        1.934001395529666e-07
                    ],
                    [
                        -2.5879011359182953e-06,
                        2.5416214587834682,
                        8.094333012234484
                    ],
                    [
                        1.6600049572890183e-08,
                        3.91998972691032e-08,
                        6.3416385474938854
                    ],
                    [
                        2.201109657541177,
                        1.2708088231565726,
                        10.13339757892562
                    ],
                    [
                        1.6099993509951914e-08,
                        3.770000717187722e-08,
                        12.172492545839896
                    ],
                    [
                        -2.5879203162182955e-06,
                        2.541621458764288,
                        13.925187010580496
                    ],
                    [
                        2.4600013288229807e-08,
                        3.279998738940312e-08,
                        18.227730591160107
                    ],
                    [
                        2.201109657520316,
                        1.2708088231357122,
                        16.475036126419507
                    ],
                    [
                        2.201109657501136,
                        1.2708088231165318,
                        22.30589012476552
                    ],
                    [
                        2.5500103416804326e-08,
                        3.389998412298704e-08,
                        24.058584589506115
                    ],
                    [
                        -2.5879411767182955e-06,
                        2.5416214587434274,
                        20.26682555807438
                    ],
                    [
                        2.2011096574812177,
                        1.2708088230966132,
                        28.361158570308863
                    ],
                    [
                        -2.5879620372182955e-06,
                        2.5416214587225667,
                        26.608464105568267
                    ]
                ],
                [
                    [
                        -2.5878811931182955e-06,
                        2.541621458803411,
                        2.031677312468847
                    ],
                    [
                        2.20110965756212,
                        1.2708088231775156,
                        3.766648447120574
                    ],
                    [
                        7.206160418444027e-09,
                        1.2425777766141359e-08,
                        1.0261899322125722e-06
                    ],
                    [
                        -2.5879011602182954e-06,
                        2.541621458783444,
                        8.101720266456775
                    ],
                    [
                        2.1726995899010043e-07,
                        1.2291338620021818e-08,
                        6.366749131805047
                    ],
                    [
                        2.201109657541177,
                        1.2708088231565726,
                        10.13339757892562
                    ],
                    [
                        4.4022152923983295,
                        1.253753421904338e-08,
                        12.165074891394468
                    ],
                    [
                        -2.5879202336182954e-06,
                        2.5416214587643706,
                        13.900076426269331
                    ],
                    [
                        1.1459745088752503e-07,
                        1.2216842518399219e-08,
                        18.235148245605533
                    ],
                    [
                        2.2011096575202336,
                        1.2708088231356296,
                        16.500146710730668
                    ],
                    [
                        2.2011096575011604,
                        1.2708088231165562,
                        22.298502870543228
                    ],
                    [
                        4.402215292380023,
                        1.2462580625786938e-08,
                        24.033474005194954
                    ],
                    [
                        -2.5879411767182955e-06,
                        2.5416214587434274,
                        20.26682555807438
                    ],
                    [
                        2.2011096574811932,
                        1.270808823096589,
                        28.368545824531154
                    ],
                    [
                        -2.587962119818295e-06,
                        2.541621458722484,
                        26.633574689879428
                    ]
                ]
            ]
        },
        "energies": {
            "@module": "numpy",
            "@class": "array",
            "dtype": "float64",
            "data": [
                -61.594882,
                -61.602602
            ]
        },
        "forces": {
            "@module": "numpy",
            "@class": "array",
            "dtype": "float64",
            "data": [
                [
                    [
                        1.14122e-05,
                        -6.4833e-06,
                        0.0454118
                    ],
                    [
                        -1.17313e-05,
                        6.55681e-06,
                        -0.116087
                    ],
                    [
                        -6.98541e-08,
                        -1.21313e-07,
                        1.50443e-05
                    ],
                    [
                        7.69533e-06,
                        -4.40235e-06,
                        -0.0454716
                    ],
                    [
                        -1.69229e-06,
                        1.10045e-06,
                        0.116138
                    ],
                    [
                        -9.29227e-06,
                        5.43276e-06,
                        6.68369e-05
                    ],
                    [
                        -3.42908e-06,
                        1.91195e-06,
                        0.0454314
                    ],
                    [
                        8.7183e-06,
                        -5.21221e-06,
                        -0.11619
                    ],
                    [
                        3.31133e-06,
                        -2.116e-06,
                        -0.0454309
                    ],
                    [
                        -8.63552e-06,
                        5.35566e-06,
                        0.11619
                    ],
                    [
                        -7.60141e-06,
                        4.56566e-06,
                        0.0454745
                    ],
                    [
                        1.56203e-06,
                        -1.3269e-06,
                        -0.116135
                    ],
                    [
                        9.3509e-06,
                        -5.3311e-06,
                        -6.70071e-05
                    ],
                    [
                        -1.13794e-05,
                        6.5395e-06,
                        -0.0454862
                    ],
                    [
                        1.1781e-05,
                        -6.46963e-06,
                        0.11614
                    ]
                ],
                [
                    [
                        1.74855e-12,
                        -3.96588e-12,
                        2.43721e-11
                    ],
                    [
                        -8.07027e-12,
                        1.73662e-12,
                        -1.02785e-11
                    ],
                    [
                        6.23945e-14,
                        1.04639e-13,
                        6.56655e-12
                    ],
                    [
                        2.59288e-11,
                        -1.18517e-11,
                        -4.01429e-12
                    ],
                    [
                        1.61369e-11,
                        -6.36444e-12,
                        -1.60005e-12
                    ],
                    [
                        1.35928e-11,
                        -7.91947e-12,
                        4.45746e-12
                    ],
                    [
                        7.84484e-12,
                        -7.84228e-12,
                        -5.93851e-12
                    ],
                    [
                        8.40239e-12,
                        -7.93077e-12,
                        -1.77391e-12
                    ],
                    [
                        -7.98828e-12,
                        7.58998e-12,
                        -1.16818e-12
                    ],
                    [
                        -8.41983e-12,
                        7.89444e-12,
                        -3.12691e-12
                    ],
                    [
                        -2.59487e-11,
                        1.18103e-11,
                        -3.38946e-12
                    ],
                    [
                        -1.62267e-11,
                        6.21367e-12,
                        3.11048e-12
                    ],
                    [
                        -1.36565e-11,
                        7.81103e-12,
                        -8.06638e-12
                    ],
                    [
                        -1.5869e-12,
                        4.24954e-12,
                        -2.76195e-11
                    ],
                    [
                        8.18084e-12,
                        -1.53569e-12,
                        2.84696e-11
                    ]
                ]
            ]
        },
        "virials": {
            "@module": "numpy",
            "@class": "array",
            "dtype": "float64",
            "data": [
                [
                    [
                        -3.401520048770969,
                        1.1925263661574172e-05,
                        -1.1004596752294162e-05
                    ],
                    [
                        1.1925263661574172e-05,
                        -3.401520048770969,
                        4.670061663955245e-08
                    ],
                    [
                        -1.1004596752294162e-05,
                        4.670061663955245e-08,
                        -3.7653394843948513
                    ]
                ],
                [
                    [
                        -2.740739241211031,
                        8.40188218657463e-06,
                        -4.941530002058105e-06
                    ],
                    [
                        8.40188218657463e-06,
                        -2.7407392093661547,
                        4.187180922103282e-09
                    ],
                    [
                        -4.941530002058105e-06,
                        4.187180922103282e-09,
                        -2.7459849840455686
                    ]
                ]
            ]
        },
        "stress": {
            "@module": "numpy",
            "@class": "array",
            "dtype": "float64",
            "data": [
                [
                    [
                        -10.68153,
                        3.7447981999999995e-05,
                        -3.4556882999999995e-05
                    ],
                    [
                        3.7447981999999995e-05,
                        -10.68153,
                        1.4665032999999999e-07
                    ],
                    [
                        -3.4556882999999995e-05,
                        1.4665032999999999e-07,
                        -11.824004
                    ]
                ],
                [
                    [
                        -8.6065312,
                        2.638378e-05,
                        -1.5517504e-05
                    ],
                    [
                        2.638378e-05,
                        -8.6065311,
                        1.314868e-08
                    ],
                    [
                        -1.5517504e-05,
                        1.314868e-08,
                        -8.623004000000002
                    ]
                ]
            ]
        }
    }
}